restview/__init__.py
restview/__main__.py
restview/favicon.ico
restview/icon-16x16.xcf
restview/oldrestview.css
restview/restview.css
restview/restviewhttp.py
restview/tests.py
restview-3.0.2.dist-info/LICENSE
restview-3.0.2.dist-info/METADATA
restview-3.0.2.dist-info/WHEEL
restview-3.0.2.dist-info/entry_points.txt
restview-3.0.2.dist-info/top_level.txt
restview-3.0.2.dist-info/RECORD
